shopee_crawler/__init__.py
shopee_crawler/crawler.py
shopee_crawler/toolkit/__init__.py
shopee_crawler/toolkit/crawl_by_cat_url.py
shopee_crawler/toolkit/crawl_by_search.py
shopee_crawler/toolkit/crawl_by_shop_url.py
shopee_crawler/toolkit/crawl_cat_list.py
shopee_crawler/toolkit/curl.py
shopee_crawler-0.1.6.dist-info/METADATA
shopee_crawler-0.1.6.dist-info/WHEEL
shopee_crawler-0.1.6.dist-info/top_level.txt
shopee_crawler-0.1.6.dist-info/RECORD
