Metadata-Version: 2.1
Name: shopee-crawler
Version: 0.1.6
Summary: Crawler for shopee
Home-page: https://github.com/lthoangg/shopee-crawler
Author: Lê Trọng Hoàng
Author-email: letronghoang00@gmail.com
License: UNKNOWN
Platform: UNKNOWN
Classifier: Programming Language :: Python :: 3
Classifier: License :: OSI Approved :: MIT License
Classifier: Operating System :: OS Independent
Requires-Python: >=3.7
